aliasanx/__init__.py
aliasanx/anx.py
aliasanx/pyanx.py
aliasanx-0.1.2.dist-info/METADATA
aliasanx-0.1.2.dist-info/WHEEL
aliasanx-0.1.2.dist-info/top_level.txt
aliasanx-0.1.2.dist-info/RECORD
