Metadata-Version: 2.4
Name: AliasAnx
Version: 0.1.2
Summary: Geração de arquivos ANX (Alias) em Python
Author-email: Cristiano Ribeiro Ritta <tiano.ritta@gmail.com>
License: Apache-2.0
Keywords: alias,anx,xml,graph,forensics,i2,IBM I2
Classifier: Programming Language :: Python :: 3
Classifier: License :: OSI Approved :: Apache Software License
Classifier: Operating System :: OS Independent
Classifier: Typing :: Typed
Requires-Python: >=3.9
